connect_four_gymnasium/ConnectFourEnv.py
connect_four_gymnasium/__init__.py
connect_four_gymnasium/players/AdultPlayer.py
connect_four_gymnasium/players/AdultSmarterPlayer.py
connect_four_gymnasium/players/BabyPlayer.py
connect_four_gymnasium/players/BabySmarterPlayer.py
connect_four_gymnasium/players/ChildPlayer.py
connect_four_gymnasium/players/ChildSmarterPlayer.py
connect_four_gymnasium/players/ConsolePlayer.py
connect_four_gymnasium/players/ModelPlayer.py
connect_four_gymnasium/players/Player.py
connect_four_gymnasium/players/SelfTrained1Player.py
connect_four_gymnasium/players/SelfTrained1PlayerWeight.pt
connect_four_gymnasium/players/SelfTrained2Player.py
connect_four_gymnasium/players/SelfTrained2PlayerWeight.pt
connect_four_gymnasium/players/SelfTrained3Player.py
connect_four_gymnasium/players/SelfTrained3PlayerWeight.pt
connect_four_gymnasium/players/SelfTrained4Player.py
connect_four_gymnasium/players/SelfTrained4PlayerWeight.pt
connect_four_gymnasium/players/SelfTrained5Player.py
connect_four_gymnasium/players/SelfTrained5PlayerWeight.pt
connect_four_gymnasium/players/SelfTrained6Player.py
connect_four_gymnasium/players/SelfTrained6PlayerWeight.pt
connect_four_gymnasium/players/SelfTrained7Player.py
connect_four_gymnasium/players/SelfTrained7PlayerWeight.pt
connect_four_gymnasium/players/SimulatePlayer.py
connect_four_gymnasium/players/TeenagerPlayer.py
connect_four_gymnasium/players/TeenagerSmarterPlayer.py
connect_four_gymnasium/players/__init__.py
connect_four_gymnasium/tools/EloLeaderboard.py
connect_four_gymnasium/tools/__init__.py
gymnasium_connect_four-1.3.5.dist-info/LICENSE
gymnasium_connect_four-1.3.5.dist-info/METADATA
gymnasium_connect_four-1.3.5.dist-info/WHEEL
gymnasium_connect_four-1.3.5.dist-info/top_level.txt
gymnasium_connect_four-1.3.5.dist-info/RECORD
