Metadata-Version: 2.1
Name: gymnasium-connect-four
Version: 1.3.5
Summary: A connect 4 (connect four) environment for OpenAI Gym and Gymnasium
Home-page: https://github.com/lucasBertola/Connect-4-env
Author: Lucas Bertola
License-File: LICENSE
Requires-Dist: pygame ==2.1.3
Requires-Dist: gymnasium ==0.28.1
